README.md
setup.py
slender/__init__.py
slender/command_line.py
slender/dictionary.py
slender/list.py
slender/set.py
slender.egg-info/PKG-INFO
slender.egg-info/SOURCES.txt
slender.egg-info/dependency_links.txt
slender.egg-info/entry_points.txt
slender.egg-info/top_level.txt