Metadata-Version: 2.1
Name: slender
Version: 0.1.3.3
Summary: Slender datastructures in Python
Home-page: http://github.com/torokmark/slender
Author: Mark Torok
License: Apache License 2.0
Project-URL: Documentation, https://slender.readthedocs.io
Project-URL: Source, https://github.com/torokmark/slender
Platform: UNKNOWN
Classifier: Programming Language :: Python :: 3.7
Classifier: Programming Language :: Python :: 3 :: Only
Requires-Python: >=3.5
